<?xml version="1.0" encoding="UTF-8"?>
<!DOCTYPE properties SYSTEM "http://java.sun.com/dtd/properties.dtd">
<properties version="1.0">
    <comment>Deutsche Sprachdatei</comment>
    <entry key="item.pocketEnchanter.name">Taschenverzauberer</entry>
    <entry key="pocketEnchanter.info">Unterwegs Gegenstände verzaubern.</entry>
    <entry key="version.fail.changelog">Changelog konnte nicht geladen werden.</entry>
    <entry key="version.update.available">Eine aktualisierte Version ist verfügbar.</entry>
    <entry key="version.beta.build">Du benutzt die Beta-Version @MOD_VERSION@. Bitte melde alle Probleme im Forum.</entry>
    <entry key="version.changelog.command">Bitte benutze das folgende Kommando um die Änderungen zu sehen:</entry>
    <entry key="positive">Ja</entry>
    <entry key="negative">Nein</entry>
    <entry key="gui.canuse">Verfügbar</entry>
    <entry key="gui.cost">Kosten</entry>
    <entry key="gui.bookshelves">Bücherregale</entry>
    <entry key="gui.playerlevel">Erfahrungslevel</entry>
    <entry key="gui.icon.enchant">Verzaubern</entry>
    <entry key="gui.icon.enchant.description">Verzauberung hinzufügen</entry>
    <entry key="gui.icon.disenchant">Entzaubern</entry>
    <entry key="gui.icon.disenchant.description">Verzauberung entfernen</entry>
    <entry key="gui.icon.bookshelves">Bücherregale</entry>
    <entry key="gui.icon.bookshelves.description">Anzahl der Bücherregale um den Zaubertisch</entry>
    <entry key="gui.icon.repair">Reparieren</entry>
    <entry key="gui.icon.repair.description">Beschädigten verzauberten Gegenstand reparieren</entry>
    <entry key="gui.icon.transfer">Verschieben</entry>
    <entry key="gui.icon.transfer.description">Verzauberungen zwischen Gegenständen verschieben</entry>
    <entry key="itemGroup.eplus">Enchanting Plus</entry>
</properties>